thefloatingdutchman/__init__.py
thefloatingdutchman/game_manager.py
thefloatingdutchman/game_settings.py
thefloatingdutchman/main.py
thefloatingdutchman/manager.py
thefloatingdutchman/menu_manager.py
thefloatingdutchman/ui.py
thefloatingdutchman/character/character_data.py
thefloatingdutchman/character/character_sprite.py
thefloatingdutchman/character/enemy/charge_enemy.py
thefloatingdutchman/character/enemy/chase_enemy.py
thefloatingdutchman/character/enemy/enemyType5.py
thefloatingdutchman/character/enemy/enemy_data.py
thefloatingdutchman/character/enemy/enemy_manager.py
thefloatingdutchman/character/enemy/enemy_sprite.py
thefloatingdutchman/character/enemy/ranged_enemy.py
thefloatingdutchman/character/enemy/ranged_teleport_enemy.py
thefloatingdutchman/character/enemy/weapon_enemy.py
thefloatingdutchman/character/enemy/boss/boss_data.py
thefloatingdutchman/character/enemy/boss/boss_manager.py
thefloatingdutchman/character/enemy/boss/charge_tele_boss.py
thefloatingdutchman/character/enemy/boss/first_boss.py
thefloatingdutchman/character/enemy/boss/minion_boss.py
thefloatingdutchman/character/player/player_data.py
thefloatingdutchman/character/player/player_manager.py
thefloatingdutchman/character/player/player_sprite.py
thefloatingdutchman/level/map/map_generator.py
thefloatingdutchman/level/room/enemy_room.py
thefloatingdutchman/level/room/room.py
thefloatingdutchman/level/room/room_manager.py
thefloatingdutchman/level/room/treasure_room.py
thefloatingdutchman/objects/drop_manager.py
thefloatingdutchman/objects/object_data.py
thefloatingdutchman/objects/object_sprite.py
thefloatingdutchman/objects/treasure_manager.py
thefloatingdutchman/objects/hearts/heart_data.py
thefloatingdutchman/objects/hearts/heart_sprite.py
thefloatingdutchman/objects/treasure_chest/treasure_data.py
thefloatingdutchman/objects/treasure_chest/treasure_sprite.py
thefloatingdutchman/objects/weapons/enemy_weapon.py
thefloatingdutchman/objects/weapons/multi_shot_weapon.py
TheFloatingDutchman-1.0.5.dist-info/LICENSE
TheFloatingDutchman-1.0.5.dist-info/METADATA
TheFloatingDutchman-1.0.5.dist-info/WHEEL
TheFloatingDutchman-1.0.5.dist-info/entry_points.txt
TheFloatingDutchman-1.0.5.dist-info/top_level.txt
TheFloatingDutchman-1.0.5.dist-info/RECORD
