Metadata-Version: 2.1
Name: TheFloatingDutchman
Version: 1.0.5
Summary: Package for The Floating Dutchman game
Home-page: https://github.com/EddieFerro/the-floating-dutchman
Author: Eddie Ferro
Author-email: eferro1@ufl.edu
License: UNKNOWN
Platform: UNKNOWN
Classifier: Programming Language :: Python :: 3
Classifier: License :: OSI Approved :: GNU General Public License v3 (GPLv3)
Classifier: Operating System :: OS Independent
Requires-Python: >=3.8
Requires-Dist: pygame (==2.0.0.dev8)
Requires-Dist: numpy (>=1.19.0)
Requires-Dist: networkx (==2.4)
Requires-Dist: ordered-set (>=3.1.1)
